{"$type":"app.bsky.feed.defs#postView","record":{"$type":"app.bsky.feed.post","text":"If Bluesky is invite only, does this mean that people were sitting on their invites until today or that Bluesky sent more invites to its waiting list or that people are suddenly giving away more invites? Hard to see how there's a correlation when signup isn't open.","reply":{"root":{"$type":"com.atproto.repo.strongRef","cid":"bafyreibyefy7bmcf4inp7gotj5q2x233b73r7tmv4f7r5akbe462tfxiha","uri":"at://did:plc:mndtiksvxikpsy3zl6ebd2kr/app.bsky.feed.post/3k7rlrukr4w2v"},"parent":{"$type":"com.atproto.repo.strongRef","cid":"bafyreibyefy7bmcf4inp7gotj5q2x233b73r7tmv4f7r5akbe462tfxiha","uri":"at://did:plc:mndtiksvxikpsy3zl6ebd2kr/app.bsky.feed.post/3k7rlrukr4w2v"}},"createdAt":"2023-09-19T21:14:01.345Z"},"author":{"did":"did:plc:uy7ehrx332p6dow5sk32hxzq","handle":"chadmichael.bsky.social","displayName":"Chad","avatar":"https://av-cdn.bsky.app/img/avatar/plain/did:plc:uy7ehrx332p6dow5sk32hxzq/bafkreihf6a3ei6ni3i4plwyh3c57qzsqllqvkcny2pbfbno26uwyftugte@jpeg","viewer":{"muted":false,"blockedBy":false},"labels":[]},"uri":"at://did:plc:uy7ehrx332p6dow5sk32hxzq/app.bsky.feed.post/3k7rmyigapw2y","cid":"bafyreifrkb2ycgkwov2cvgyx245b3dzdkz3fcf6rhkxplmbujbe747jjli","replyCount":2,"repostCount":0,"likeCount":1,"viewer":{},"labels":[],"indexedAt":"2023-09-19T21:14:01.345Z"}
